mlx_dev_server/app.py
mlx_dev_server/handlers.py
mlx_dev_server/models.py
mlx_dev_server/api/__init__.py
mlx_dev_server/api/base.py
mlx_dev_server/api/chat_completions.py
mlx_dev_server/api/completions.py
mlx_dev_server/cli/__init__.py
mlx_dev_server/cli/server.py
mlx_dev_server-0.1.1.dist-info/METADATA
mlx_dev_server-0.1.1.dist-info/WHEEL
mlx_dev_server-0.1.1.dist-info/entry_points.txt
mlx_dev_server-0.1.1.dist-info/licenses/LICENSE
mlx_dev_server-0.1.1.dist-info/RECORD
