Metadata-Version: 2.4
Name: mlx-dev-server
Version: 0.1.1
Summary: A server to run MLX models locally, optimized for code completion
Project-URL: Repository, https://github.com/toogle/mlx-dev-server
Project-URL: Issues, https://github.com/toogle/mlx-dev-server/issues
Author: Andrey Usenok
License-Expression: MIT
License-File: LICENSE
Keywords: code completion,llm,local copilot,mlx server
Classifier: Development Status :: 3 - Alpha
Classifier: Environment :: GPU
Classifier: Environment :: MacOS X
Classifier: Framework :: aiohttp
Classifier: Intended Audience :: Developers
Classifier: License :: OSI Approved :: MIT License
Classifier: Programming Language :: Python :: 3
Classifier: Programming Language :: Python :: 3.11
Classifier: Programming Language :: Python :: 3.12
Classifier: Programming Language :: Python :: Implementation :: CPython
Requires-Python: >=3.11
Requires-Dist: aiohttp>=3.11.12
Requires-Dist: colorlog>=6.9.0
Requires-Dist: huggingface-hub>=0.29.1
Requires-Dist: mlx-lm>=0.21.4; sys_platform == 'darwin' and platform_machine == 'arm64' and python_version >= '3.8' and platform_release >= '22.6.0'
